{
	"swagger": "2.0",
	"info": {
		"title": "sardius API",
		"description": "This is an sardiusAPI, which is part of the English Language API Recipe Book.",
		"termsOfService": "http://apievangelist.com/terms-of-service.html",
		"version": "v1"
	},
	"host": "s.example.com",
	"basePath": "/",
	"schemes": ["http"],
	"produces": ["application/json"],
	"paths": {
		"/sardius/": {
			"get": {
				"summary": "sardius item",
				"description": "returns an sardius item",
				"operationId": "getsardius",
				"parameters": [{
					"name": "q",
					"in": "query",
					"description": "Keyword search for item",
					"required": false,
					"type": "string"
				}],
				"responses": {
					"200": {
						"description": "A successful response.",
						"schema": {
							"type": "array",
							"items": {
								"$ref": "#/definitions/item"
							}
						}
					}
				},
				"tags": ["sardius"]
			},
			"post": {
				"summary": "sardius item",
				"description": "adds an sardius item",
				"operationId": "addsardius",
				"parameters": [{
					"name": "name",
					"in": "formData",
					"description": "Name of item",
					"required": true,
					"type": "string"
				},
				{
					"name": "description",
					"in": "formData",
					"description": "Description of item",
					"required": true,
					"type": "string"
				}],
				"responses": {
					"200": {
						"description": "A successful response.",
						"schema": {
							"type": "array",
							"items": {
								"$ref": "#/definitions/item"
							}
						}
					}
				},
				"tags": ["sardius"]
			}
		},
		"/sardius/{id}/": {
			"get": {
				"summary": "sardius item",
				"description": "returns a single sardius item",
				"operationId": "getsardiusItem",
				"parameters": [{
					"name": "id",
					"in": "path",
					"description": "Unique id for item",
					"required": true,
					"type": "integer"
				}],
				"responses": {
					"200": {
						"description": "A successful response.",
						"schema": {
							"type": "array",
							"items": {
								"$ref": "#/definitions/item"
							}
						}
					}
				},
				"tags": ["sardius"]
			},
			"put": {
				"summary": "sardius item",
				"description": "update a single sardius item",
				"operationId": "updatesardiusItem",
				"parameters": [{
					"name": "id",
					"in": "path",
					"description": "Unique id for item",
					"required": true,
					"type": "integer"
				},
				{
					"name": "name",
					"in": "formData",
					"description": "Name of item",
					"required": true,
					"type": "string"
				},
				{
					"name": "description",
					"in": "formData",
					"description": "Description of item",
					"required": true,
					"type": "string"
				}],
				"responses": {
					"200": {
						"description": "A successful response.",
						"schema": {
							"type": "array",
							"items": {
								"$ref": "#/definitions/item"
							}
						}
					}
				},
				"tags": ["sardius"]
			},
			"delete": {
				"summary": "sardius item",
				"description": "deletes a single sardius item",
				"operationId": "deletesardiusItem",
				"parameters": [{
					"name": "id",
					"in": "path",
					"description": "Unique id for item",
					"required": true,
					"type": "integer"
				}],
				"responses": {
					"200": {
						"description": "A successful response.",
						"schema": {
							"type": "array",
							"items": {
								"$ref": "#/definitions/item"
							}
						}
					}
				},
				"tags": ["sardius"]
			}
		}
	},
	"definitions": {
		"item": {
			"properties": {
				"name": {
					"description": "The name of this item.",
					"type": "string"
				},
				"description": {
					"description": "The description of this item.",
					"type": "string"
				}
			}
		}
	}
}